sso_apigee_client/__init__.py
sso_apigee_client/apigee_client.py
sso_apigee_client/auth.py
sso_apigee_client/exceptions.py
sso_apigee_client/fastapi_integration.py
sso_apigee_client/models.py
sso_apigee_client/momrah_sso_client.py
sso_apigee_client/momrah_sso_integration.py
sso_apigee_client-2.7.0.dist-info/licenses/LICENSE
sso_apigee_client-2.7.0.dist-info/METADATA
sso_apigee_client-2.7.0.dist-info/WHEEL
sso_apigee_client-2.7.0.dist-info/top_level.txt
sso_apigee_client-2.7.0.dist-info/RECORD
