Metadata-Version: 2.4
Name: sso-apigee-client
Version: 2.7.0
Summary: Python client library for APIGEE Service and MOMRAH SSO authentication
Home-page: https://github.com/yourorg/sso-apigee-service
Author: Your Organization
Author-email: Your Organization <dev@yourorg.com>
License: MIT
Project-URL: Homepage, https://github.com/yourorg/sso-apigee-service
Project-URL: Documentation, https://github.com/yourorg/sso-apigee-service
Project-URL: Repository, https://github.com/yourorg/sso-apigee-service
Project-URL: Issues, https://github.com/yourorg/sso-apigee-service/issues
Keywords: apigee,api,gateway,client,sdk,fastapi,momrah,sso,oauth,oidc,authentication
Classifier: Development Status :: 4 - Beta
Classifier: Intended Audience :: Developers
Classifier: Topic :: Software Development :: Libraries :: Python Modules
Classifier: License :: OSI Approved :: MIT License
Classifier: Programming Language :: Python :: 3
Classifier: Programming Language :: Python :: 3.9
Classifier: Programming Language :: Python :: 3.10
Classifier: Programming Language :: Python :: 3.11
Classifier: Programming Language :: Python :: 3.12
Classifier: Framework :: FastAPI
Classifier: Framework :: AsyncIO
Requires-Python: >=3.9
License-File: LICENSE
Requires-Dist: httpx>=0.25.0
Requires-Dist: pydantic>=2.5.0
Requires-Dist: python-jose[cryptography]>=3.3.0
Provides-Extra: fastapi
Requires-Dist: fastapi>=0.104.0; extra == "fastapi"
Provides-Extra: dev
Requires-Dist: pytest>=7.4.0; extra == "dev"
Requires-Dist: pytest-asyncio>=0.21.0; extra == "dev"
Requires-Dist: black>=23.0.0; extra == "dev"
Requires-Dist: mypy>=1.5.0; extra == "dev"
Requires-Dist: ruff>=0.1.0; extra == "dev"
Dynamic: author
Dynamic: home-page
Dynamic: license-file
Dynamic: requires-python
